qm_sim/__init__.py
qm_sim/cpp/CMakeLists.txt
qm_sim/cpp/__init__.py
qm_sim/cpp/eigen/CMakeLists.txt
qm_sim/cpp/eigen/__init__.py
qm_sim/cpp/eigen/include/HamiltonianBase.hpp
qm_sim/cpp/eigen/include/eigensolver.hpp
qm_sim/cpp/eigen/scripts/generate_init.py
qm_sim/cpp/eigen/src/HamiltonianBase.cpp
qm_sim/cpp/eigen/src/eigensolver.cpp
qm_sim/cpp/eigen/wrapper/CMakeLists.txt
qm_sim/cpp/eigen/wrapper/py_interface.cpp
qm_sim/eigensolvers/__init__.py
qm_sim/eigensolvers/pytorch_eigen.py
qm_sim/eigensolvers/scipy_eigen.py
qm_sim/hamiltonian/__init__.py
qm_sim/hamiltonian/spatial_hamiltonian.py
qm_sim/nature_constants.py
qm_sim/plot.py
qm_sim/spatial_derivative/__init__.py
qm_sim/spatial_derivative/cartesian.py
qm_sim/temporal_solver/__init__.py
qm_sim/temporal_solver/base.py
qm_sim/temporal_solver/crank_nicolson.py
qm_sim/temporal_solver/leapfrog.py
qm_sim/temporal_solver/scipy_solvers.py
qm_sim-0.1.2.dist-info/METADATA
qm_sim-0.1.2.dist-info/WHEEL
qm_sim-0.1.2.dist-info/entry_points.txt
qm_sim-0.1.2.dist-info/licenses/LICENSE
qm_sim-0.1.2.dist-info/RECORD
