Metadata-Version: 2.1
Name: qm-sim
Version: 0.1.2
Summary: Quantum mechanics simulation library
Author-Email: Viljar Femoen <author@example.com>
Classifier: Development Status :: 3 - Alpha
Classifier: Intended Audience :: Science/Research
Classifier: Topic :: Scientific/Engineering :: Physics
Classifier: License :: OSI Approved :: MIT License
Classifier: Programming Language :: Python :: 3
Classifier: Operating System :: OS Independent
Project-URL: Homepage, https://viljarjf.github.io/QM_sim/
Project-URL: Bug tracker, https://github.com/viljarjf/QM_sim/issues
Project-URL: Source, https://github.com/viljarjf/QM_sim
Requires-Python: >=3.10
Requires-Dist: numpy>=1.23
Requires-Dist: scipy>=1.10
Requires-Dist: tqdm>=4.64.1
Requires-Dist: matplotlib>=3.6
Requires-Dist: pytest; extra == "test"
Requires-Dist: matplotlib; extra == "test"
Requires-Dist: torch; extra == "torch"
Requires-Dist: sphinx; extra == "docs"
Requires-Dist: sphinx-rtd-theme; extra == "docs"
Requires-Dist: sphinx-mdinclude; extra == "docs"
Requires-Dist: black; extra == "linting"
Requires-Dist: isort; extra == "linting"
Requires-Dist: pylint; extra == "linting"
Provides-Extra: test
Provides-Extra: torch
Provides-Extra: docs
Provides-Extra: linting
License-File: LICENSE
